flute/__init__.py
flute/apps/__init__.py
flute/apps/amber/__init__.py
flute/apps/amber/const.py
flute/apps/amber/task.py
flute/apps/amber/template/docker-stack-template.yml
flute/apps/importer/__init__.py
flute/apps/importer/client.py
flute/apps/importer/client_bak.py
flute/apps/importer/task.py
flute/apps/importer/test/__init__.py
flute/commands/__init__.py
flute/commands/command.py
flute/libs/__init__.py
flute/libs/async_mysql_conn.py
test/__init__.py
nebula_flute-1.0.5.dist-info/LICENSE
nebula_flute-1.0.5.dist-info/METADATA
nebula_flute-1.0.5.dist-info/WHEEL
nebula_flute-1.0.5.dist-info/entry_points.txt
nebula_flute-1.0.5.dist-info/top_level.txt
nebula_flute-1.0.5.dist-info/RECORD
