Metadata-Version: 2.1
Name: nebula-flute
Version: 1.0.5
Summary: nebula graph database toolkit python version
Home-page: https://github.com/gumupaier/flute
Author: henson
Author-email: henson_wu@foxmail.com
License: UNKNOWN
Platform: UNKNOWN
Requires-Dist: aiomysql
Requires-Dist: blessed
Requires-Dist: cffi
Requires-Dist: cryptography
Requires-Dist: future
Requires-Dist: gevent
Requires-Dist: greenlet
Requires-Dist: httplib2
Requires-Dist: inquirer
Requires-Dist: nebula-python
Requires-Dist: pycparser
Requires-Dist: PyMySQL
Requires-Dist: python-editor
Requires-Dist: PyYAML
Requires-Dist: readchar
Requires-Dist: six
Requires-Dist: click
Requires-Dist: wcwidth
Requires-Dist: zope.event
Requires-Dist: zope.interface
